pyhfm/__init__.py
pyhfm/constants.py
pyhfm/exceptions.py
pyhfm/utils.py
pyhfm/api/__init__.py
pyhfm/api/loaders.py
pyhfm/core/__init__.py
pyhfm/core/file_parser.py
pyhfm/core/metadata_parser.py
pyhfm/core/parser.py
pyhfm/core/setpoint_parser.py
pyhfm/extractors/__init__.py
pyhfm/extractors/data_extractor.py
pyhfm-0.1.0.dist-info/METADATA
pyhfm-0.1.0.dist-info/WHEEL
pyhfm-0.1.0.dist-info/entry_points.txt
pyhfm-0.1.0.dist-info/licenses/LICENSE.txt
pyhfm-0.1.0.dist-info/RECORD
