Metadata-Version: 2.4
Name: pyhfm
Version: 0.1.0
Summary: Python package for reading and analyzing Heat Flow Meter (HFM) data files
Project-URL: Homepage, https://github.com/GraysonBellamy/pyhfm
Project-URL: Repository, https://github.com/GraysonBellamy/pyhfm
Project-URL: Issues, https://github.com/GraysonBellamy/pyhfm/issues
Author-email: Grayson Bellamy <gbellamy@umd.edu>
License: MIT
License-File: LICENSE.txt
Keywords: data analysis,heat flow meter,materials science,thermal analysis
Classifier: Development Status :: 3 - Alpha
Classifier: Intended Audience :: Science/Research
Classifier: License :: OSI Approved :: MIT License
Classifier: Programming Language :: Python :: 3
Classifier: Programming Language :: Python :: 3.10
Classifier: Programming Language :: Python :: 3.11
Classifier: Programming Language :: Python :: 3.12
Classifier: Topic :: Scientific/Engineering
Requires-Python: >=3.10
Requires-Dist: chardet>=5.0.0
Requires-Dist: numpy>=1.20.0
Requires-Dist: polars>=0.20.0
Requires-Dist: pre-commit>=4.3.0
Requires-Dist: pyarrow>=10.0.0
Provides-Extra: all
Requires-Dist: bandit>=1.7.0; extra == 'all'
Requires-Dist: build>=1.0.0; extra == 'all'
Requires-Dist: mkdocs-material>=9.0.0; extra == 'all'
Requires-Dist: mkdocs>=1.5.0; extra == 'all'
Requires-Dist: mkdocstrings[python]>=0.20.0; extra == 'all'
Requires-Dist: mypy>=1.5.0; extra == 'all'
Requires-Dist: pre-commit>=3.0.0; extra == 'all'
Requires-Dist: pytest-benchmark>=4.0.0; extra == 'all'
Requires-Dist: pytest-cov>=4.0.0; extra == 'all'
Requires-Dist: pytest-xdist>=3.0.0; extra == 'all'
Requires-Dist: pytest>=7.0.0; extra == 'all'
Requires-Dist: ruff>=0.1.0; extra == 'all'
Requires-Dist: twine>=4.0.0; extra == 'all'
Provides-Extra: build
Requires-Dist: build>=1.0.0; extra == 'build'
Requires-Dist: twine>=4.0.0; extra == 'build'
Provides-Extra: dev
Requires-Dist: bandit>=1.7.0; extra == 'dev'
Requires-Dist: mypy>=1.5.0; extra == 'dev'
Requires-Dist: pre-commit>=3.0.0; extra == 'dev'
Requires-Dist: ruff>=0.1.0; extra == 'dev'
Provides-Extra: docs
Requires-Dist: mkdocs-material>=9.0.0; extra == 'docs'
Requires-Dist: mkdocs>=1.5.0; extra == 'docs'
Requires-Dist: mkdocstrings[python]>=0.20.0; extra == 'docs'
Provides-Extra: performance
Requires-Dist: pytest-benchmark>=4.0.0; extra == 'performance'
Provides-Extra: test
Requires-Dist: pytest-cov>=4.0.0; extra == 'test'
Requires-Dist: pytest-xdist>=3.0.0; extra == 'test'
Requires-Dist: pytest>=7.0.0; extra == 'test'
